{"tags": {"html": 1, "head": 1, "style": 41, "meta": 17, "link": 18, "title": 1, "script": 33, "body": 1, "a": 98, "div": 234, "section": 13, "header": 1, "span": 41, "svg": 45, "metadata": 33, "x:xmpmeta": 33, "rdf:rdf": 33, "rdf:description": 33, "defs": 33, "path": 72, "g": 6, "rect": 6, "nav": 3, "ul": 15, "li": 62, "ol": 1, "img": 17, "form": 8, "input": 23, "button": 14, "label": 13, "circle": 2, "h5": 5, "u": 6, "p": 23, "h4": 1, "main": 1, "video": 1, "source": 1, "h3": 7, "footer": 1, "strong": 3, "address": 1, "h1": 3, "select": 1, "option": 255, "figure": 3, "figcaption": 3, "polygon": 3}, "ping": 0.563549, "ssl": true, "termsInTitle": [0], "termInUrl": 11, "termsInPage": [1078, 1103, 1196, 1439, 1697, 1757, 1811, 1950, 2193, 2404, 2500, 2743, 12111, 12367, 12537, 12885, 13000, 13415, 13564, 13670, 14260, 14525, 19797, 32749, 33190, 33279, 36816, 64202, 69712, 72346, 72468, 72623, 72729, 72869, 73473, 90725, 90935, 91553, 91730, 94833, 95010, 98125, 98339, 101485, 101699, 116002, 116889, 116917, 117420, 134481, 140972, 144165, 148232, 151751, 154619, 190163, 190191, 190570, 190598, 201911, 204183, 210820, 210875], "url": "https://us.sirthelabel.com/", "robots": true, "errors": 545}