{"tags": {"html": 1, "head": 1, "meta": 27, "link": 41, "title": 1, "script": 61, "style": 4, "noscript": 1, "body": 1, "div": 86, "header": 1, "a": 236, "img": 23, "i": 10, "span": 27, "button": 2, "nav": 1, "ul": 13, "li": 60, "h4": 7, "form": 5, "input": 10, "h1": 1, "p": 71, "strong": 116, "br": 73, "table": 2, "tbody": 1, "tr": 30, "td": 46, "u": 3, "h3": 11, "footer": 1, "label": 1}, "ping": 0.167885, "ssl": true, "termsInTitle": [-1], "termInUrl": -1, "termsInPage": [1449, 1489, 1556, 2271, 2311, 2378, 26792, 27799, 28869, 30476, 31526, 32989, 34024, 35362, 36402, 37455, 39213, 40242, 41694, 42701, 44175, 45204, 46799, 47654, 47840], "url": "https://ragbrai.com/routemaps/2019-route-maps/", "robots": true, "errors": 2}