{"tags": {"html": 1, "head": 1, "title": 1, "meta": 69, "link": 11, "script": 17, "style": 2, "body": 1, "div": 132, "header": 9, "section": 8, "button": 9, "svg": 24, "rect": 10, "span": 28, "path": 26, "a": 176, "circle": 1, "main": 1, "ul": 19, "li": 159, "article": 1, "p": 42, "h1": 1, "figure": 5, "img": 1, "figcaption": 5, "time": 5, "aside": 6, "h3": 7, "h2": 6, "nav": 2, "polygon": 5, "footer": 1, "noscript": 1, "iframe": 1}, "ping": 0.124424, "ssl": true, "termsInTitle": [21], "termInUrl": -1, "termsInPage": [278, 2259, 2928, 26999, 134251, 140218, 140827, 141945, 142062, 144655, 148178, 148785, 149901, 150018, 151627, 153891, 154394, 163695, 164302, 165418, 165535, 215008, 215151, 285624, 285734, 319460, 445831, 449615, 450273, 464962], "url": "https://www.nytimes.com/2019/07/22/us/politics/budget-deal.html", "robots": true, "errors": 36}