{"tags": {"html": 1, "head": 1, "script": 18, "meta": 16, "title": 1, "link": 8, "noscript": 3, "body": 1, "iframe": 1, "div": 52, "nav": 3, "ul": 7, "li": 41, "a": 52, "header": 1, "span": 3, "strong": 1, "button": 1, "p": 11, "form": 1, "input": 5, "h2": 2, "h3": 3, "section": 1, "img": 18, "footer": 1, "h4": 1, "em": 1}, "ping": 0.313421, "ssl": true, "termsInTitle": [0], "termInUrl": 22, "termsInPage": [3127, 3209, 3301, 3850, 4882, 14242, 14976, 16634, 16651, 17446, 17636, 17653, 17964, 17981, 19121, 19156, 19399, 19510, 20550, 20561, 20637, 20656, 20685, 20773, 20867, 20915, 20946, 20963, 21132, 21163, 21180, 21195, 21319, 21373, 21404, 21421, 21438, 21551, 21793, 21811, 21842, 22038, 22209, 23100, 25114, 25136], "url": "https://www.raise.com/sell-gift-cards", "robots": true, "errors": 1}