{"tags": {"html": 1, "head": 1, "meta": 1, "title": 1, "link": 8, "script": 4, "body": 1, "style": 1, "nav": 1, "div": 7, "button": 1, "span": 10, "ul": 16, "li": 104, "a": 106, "b": 3, "aside": 1, "h3": 1, "main": 1, "gcse:search": 1, "article": 1, "h1": 1, "p": 4, "img": 3}, "ping": 0.248991, "ssl": true, "termsInTitle": [0], "termInUrl": 30, "termsInPage": [70, 198, 13343, 13372, 13465, 13519, 13563, 13643, 13739, 13800, 14583, 14883, 14960], "url": "https://voicethread.com/howto/private-reply-to-a-comment/", "robots": true, "errors": 8}