{"tags": {"html": 1, "head": 1, "meta": 18, "script": 129, "title": 2, "link": 13, "noscript": 3, "body": 1, "div": 729, "style": 2, "span": 478, "a": 550, "form": 2, "button": 6, "input": 17, "select": 1, "option": 6, "ul": 20, "li": 96, "p": 39, "h5": 12, "br": 74, "strong": 13, "small": 6, "img": 88, "section": 1, "svg": 12, "g": 4, "rect": 1, "text": 1, "tspan": 1, "path": 33, "polygon": 4, "h2": 13, "textarea": 1, "h1": 1, "time": 2, "h4": 28, "h3": 15, "i": 3, "iframe": 1, "b": 37, "table": 2, "tr": 18, "td": 70, "em": 1, "hr": 13, "nobr": 1}, "ping": 0.574502, "ssl": true, "termsInTitle": [0, -1], "termInUrl": -1, "termsInPage": [684, 3953, 4064, 4339, 4698, 5136, 6480, 6671, 6788, 7600, 8580, 8835, 8961, 10173, 45946, 46689, 47602, 47626, 51980, 60386, 69593, 69645, 70336, 71272, 71483, 79938, 80498, 80563, 80977, 81017, 81493, 81558, 81978, 82023, 82464, 82531, 82951, 82996, 167477, 168485, 168529, 179892, 180877, 181132, 181257], "url": "https://www.imdb.com/title/tt0126886/", "robots": true, "errors": 139}