{"tags": {"html": 1, "head": 1, "meta": 3, "title": 1, "link": 7, "body": 1, "header": 1, "div": 17, "ul": 3, "li": 13, "a": 13, "img": 7, "article": 1, "span": 8, "p": 2, "small": 1, "button": 1, "iframe": 1, "footer": 1, "script": 3}, "ping": 0.353954, "ssl": false, "termsInTitle": [0], "termInUrl": 11, "termsInPage": [79, 187, 612, 720, 799, 879, 959, 1042, 1290, 1362, 1437, 1576, 1667, 1758, 1849, 2154, 2182, 2201, 3973, 4081, 5083, 5167, 5243, 5347], "url": "http://www.human-themovie.org/", "robots": true, "errors": 3}