{"tags": {"html": 1, "head": 1, "meta": 7, "title": 1, "script": 6, "link": 53, "body": 1, "div": 98, "a": 1410, "h1": 1, "p": 58, "table": 13, "tbody": 13, "tr": 108, "th": 32, "td": 292, "img": 9, "br": 17, "span": 584, "abbr": 23, "b": 83, "sup": 103, "i": 303, "input": 7, "h2": 20, "label": 2, "ul": 49, "li": 768, "h3": 24, "blockquote": 1, "ol": 1, "cite": 33, "style": 1, "bdi": 2, "noscript": 1, "form": 1}, "ping": 0.098203, "ssl": true, "termsInTitle": [-1], "termInUrl": -1, "termsInPage": [11332, 11363, 11420, 11448, 11469, 15161, 15230, 24303, 24349, 50533, 50545, 50730, 50909, 50940, 50988, 51016, 51037, 52043, 53150, 54714, 76884, 76912, 76933, 76988, 77019, 81418, 81446, 81467, 81693, 81927, 117561, 117650], "url": "https://en.wikipedia.org/wiki/Peter_Finch", "robots": true, "errors": 92}