{"tags": {"html": 1, "head": 1, "title": 1, "meta": 9, "link": 15, "style": 2, "script": 6, "body": 1, "div": 73, "header": 1, "nav": 6, "a": 150, "img": 3, "button": 1, "span": 6, "ul": 17, "li": 77, "input": 1, "i": 22, "h1": 1, "p": 5, "vcom:progress": 1, "vcom:qpreview": 1, "vcom:addtolist": 1, "vcom:share": 1, "h3": 17, "dl": 7, "dt": 7, "dd": 14, "vcom:wordfamily": 1, "vcom:examples": 1, "section": 1, "h2": 1, "br": 2, "footer": 1}, "ping": 0.186247, "ssl": true, "termsInTitle": [0], "termInUrl": 38, "termsInPage": [66, 362, 558, 966, 12818, 12894, 12974, 13287, 13539, 13589, 13691, 13740, 13992, 14041, 14139, 14236, 14412, 14780, 15217, 15566, 15593, 16832, 16859, 21282, 21322, 21386, 21522, 21582, 21717, 21865, 21927, 22061, 22125, 22259, 22319, 22487, 22620, 22658, 22789, 22827, 23084], "url": "https://www.vocabulary.com/dictionary/spite", "robots": true, "errors": 34}