{"tags": {"html": 1, "head": 1, "meta": 3, "title": 1, "link": 1, "script": 3, "style": 1, "body": 1, "div": 20, "ul": 3, "li": 29, "a": 36, "img": 6, "form": 1, "input": 6, "br": 2, "noscript": 1}, "ping": 0.13097, "ssl": true, "termsInTitle": [0], "termInUrl": 26, "termsInPage": [398, 587, 933, 987, 1062, 1143, 1289, 1337, 6832, 6880, 7759, 7774, 8559, 8661, 8689, 8843, 10224, 10536, 10551, 11318, 11481, 11796, 12002, 12225], "url": "https://www.msn.com/en-us/entertainment", "robots": true, "errors": 5}