{"tags": {"html": 1, "head": 1, "meta": 19, "link": 9, "script": 38, "title": 1, "body": 1, "noscript": 2, "iframe": 1, "img": 11, "main": 1, "div": 157, "header": 1, "a": 105, "ul": 10, "li": 51, "span": 75, "em": 23, "form": 5, "label": 5, "input": 8, "button": 14, "strong": 10, "small": 1, "article": 1, "select": 1, "option": 6, "textarea": 1, "p": 10, "h1": 1, "section": 4, "h2": 7, "figure": 2, "figcaption": 2, "cite": 2, "sup": 1, "sub": 1, "aside": 1, "dl": 1, "dt": 1, "dd": 1, "footer": 1, "br": 4, "hr": 1, "style": 1}, "ping": 0.451185, "ssl": true, "termsInTitle": [0], "termInUrl": 35, "termsInPage": [491, 826, 954, 1212, 1280, 2331, 3602, 3984, 4045, 4480, 4755, 4787, 5221, 5254, 15664, 20538, 26992, 27080, 27130, 28091, 28650, 33474, 33531, 34224, 34305, 34404, 34427, 34504, 34603, 35654, 36337, 37150, 37248, 37434, 37484, 38621, 38765, 38796, 39168, 39218, 39405, 39481, 39599, 39760, 39970, 40051, 40399, 40753, 41030, 41380, 43628, 45025, 45073, 45831, 47214, 50194, 50312, 50704, 51085, 51097, 51394, 51408, 51478, 51549, 51564, 54764, 55884], "url": "https://www.britannica.com/science/tooth-anatomy", "robots": true, "errors": 26}