{"tags": {"html": 1, "head": 1, "script": 21, "meta": 11, "link": 8, "title": 1, "style": 116, "body": 1, "noscript": 2, "iframe": 1, "div": 47, "header": 1, "nav": 2, "ul": 12, "li": 109, "a": 113, "button": 3, "span": 96, "img": 5, "form": 1, "label": 1, "input": 1, "main": 1, "aside": 18, "section": 7, "h1": 1, "audio": 2, "source": 3, "em": 8, "strong": 4, "p": 19, "hr": 1, "h2": 2, "footer": 1}, "ping": 0.114957, "ssl": true, "termsInTitle": [0], "termInUrl": 33, "termsInPage": [236, 349, 426, 658, 739, 1463, 1480, 32841, 36913, 38205, 38285, 41569, 46487, 46546, 49340, 49401, 50222, 55234, 55884, 55989, 56072, 56134, 56224, 56303, 56362, 56442, 56512, 56577, 80554, 80586, 80622, 80638, 83718, 83742, 83766, 85655, 85679, 85703, 88571, 88594, 88617, 93207, 101802, 102193, 102559, 102907, 103291, 103657, 104000, 104371, 104756, 105113, 105532], "url": "https://www.thesaurus.com/browse/showed", "robots": true, "errors": 140}